goodwe/__init__.py
goodwe/const.py
goodwe/dt.py
goodwe/es.py
goodwe/et.py
goodwe/exceptions.py
goodwe/goodwe.py
goodwe/inverter.py
goodwe/modbus.py
goodwe/processor.py
goodwe/protocol.py
goodwe/sensor.py
goodwe/xs.py
tests/__init__.py
tests/inverter_check.py
tests/inverter_scan.py
tests/test_dt.py
tests/test_es.py
tests/test_et.py
tests/test_goodwe.py
tests/test_modbus.py
tests/test_processor.py
tests/test_protocol.py
tests/test_sensor.py
goodwe_louigie-1.0.1.dist-info/LICENSE
goodwe_louigie-1.0.1.dist-info/METADATA
goodwe_louigie-1.0.1.dist-info/WHEEL
goodwe_louigie-1.0.1.dist-info/top_level.txt
goodwe_louigie-1.0.1.dist-info/RECORD
