Metadata-Version: 2.1
Name: goodwe-louigie
Version: 1.0.1
Summary: Read data from GoodWe inverter via local network
Home-page: https://github.com/marcelblijleven/goodwe
Author: Marcel Blijleven, Martin Letenay
Author-email: 'marcelblijleven@gmail.com
License: MIT
Keywords: GoodWe,Solar Panel,Inverter,Photovoltaics,PV
Platform: UNKNOWN
Classifier: Development Status :: 4 - Beta
Classifier: Intended Audience :: Developers
Classifier: Topic :: Software Development :: Libraries :: Python Modules
Classifier: License :: OSI Approved :: MIT License
Classifier: Programming Language :: Python :: 3
Classifier: Programming Language :: Python :: 3.7
Classifier: Programming Language :: Python :: 3.8
Classifier: Programming Language :: Python :: 3.9
License-File: LICENSE
